hiddenv/__init__.py
hiddenv/conf.py
hiddenv/config.py
hiddenv/dotenv.py
hiddenv/environment.py
hiddenv/environment.pyi
hiddenv/py.typed
hiddenv-2021.11.8.dist-info/LICENSE
hiddenv-2021.11.8.dist-info/METADATA
hiddenv-2021.11.8.dist-info/WHEEL
hiddenv-2021.11.8.dist-info/top_level.txt
hiddenv-2021.11.8.dist-info/RECORD
