Metadata-Version: 2.1
Name: hiddenv
Version: 2021.11.8
Summary: Utility for managing .env-sourced settings across multiple packages
Home-page: https://gitlab.com/k377u/hiddenv
Author: Roope Tikkanen <roope@k377u.com> & Daniil Iakovlev <daniil.iakovlev@gmail.com>
Author-email: hiddenv@k377u.com
Maintainer: Roope Tikkanen <roope@k377u.com> & Daniil Iakovlev <daniil.iakovlev@gmail.com>
Maintainer-email: hiddenv@k377u.com
License: MIT License
Keywords: dotenv,settings
Platform: UNKNOWN
Classifier: Development Status :: 5 - Production/Stable
Classifier: Intended Audience :: Developers
Classifier: Intended Audience :: Information Technology
Classifier: License :: OSI Approved
Classifier: License :: OSI Approved :: MIT License
Classifier: Operating System :: OS Independent
Classifier: Programming Language :: Python
Classifier: Programming Language :: Python :: 3
Classifier: Programming Language :: Python :: 3 :: Only
Classifier: Programming Language :: Python :: 3.8
Classifier: Programming Language :: Python :: 3.9
Classifier: Typing :: Typed
Classifier: Framework :: Django
Classifier: Topic :: Software Development
Classifier: Topic :: Software Development :: Libraries
Classifier: Topic :: Software Development :: Libraries :: Python Modules
Requires-Python: >=3.8
License-File: LICENSE
Requires-Dist: docstring-parser
Provides-Extra: dev
Requires-Dist: django ; extra == 'dev'
Requires-Dist: pytest ; extra == 'dev'
Requires-Dist: pytest-cov ; extra == 'dev'
Requires-Dist: pytest-html ; extra == 'dev'
Requires-Dist: pycodestyle ; extra == 'dev'
Requires-Dist: pylint ; extra == 'dev'
Requires-Dist: pylint-json2html ; extra == 'dev'
Requires-Dist: flake8 ; extra == 'dev'
Requires-Dist: twine ; extra == 'dev'
Requires-Dist: isort ; extra == 'dev'
Requires-Dist: yapf ; extra == 'dev'
Requires-Dist: mypy ; extra == 'dev'
